traincv/__init__.py
traincv/app.py
traincv/storage.py
traincv/common/__init__.py
traincv/common/gpu_util.py
traincv/configs/__init__.py
traincv/configs/labelme_config.yaml
traincv/configs/yolov5_data.yaml
traincv/models/__init__.py
traincv/models/project.py
traincv/models/tablemodel.py
traincv/resources/__init__.py
traincv/resources/resources.py
traincv/services/__init__.py
traincv/services/system_monitor.py
traincv/services/yolov5.py
traincv/trainer/__init__.py
traincv/trainer/core/__init__.py
traincv/trainer/core/constants.py
traincv/trainer/core/exceptions.py
traincv/trainer/core/project.py
traincv/trainer/core/tasks.py
traincv/trainer/data/__init__.py
traincv/trainer/data/data_preparation.py
traincv/trainer/data/data_subset_preparator.py
traincv/views/__init__.py
traincv/views/maintabs.py
traincv/views/mainwindow.py
traincv/views/common/__init__.py
traincv/views/common/tableview.py
traincv/views/common/toaster.py
traincv/views/labeling/__init__.py
traincv/views/labeling/labeling_wrapper.py
traincv/views/labeling/labelme/__init__.py
traincv/views/labeling/labelme/__main__.py
traincv/views/labeling/labelme/config.py
traincv/views/labeling/labelme/label_file.py
traincv/views/labeling/labelme/labelme_widget.py
traincv/views/labeling/labelme/logger.py
traincv/views/labeling/labelme/shape.py
traincv/views/labeling/labelme/testing.py
traincv/views/labeling/labelme/tracker.py
traincv/views/labeling/labelme/icons/app.icns
traincv/views/labeling/labelme/icons/app.png
traincv/views/labeling/labelme/icons/app.svg
traincv/views/labeling/labelme/icons/brain.png
traincv/views/labeling/labelme/icons/cancel.png
traincv/views/labeling/labelme/icons/cartesian.png
traincv/views/labeling/labelme/icons/circle.png
traincv/views/labeling/labelme/icons/color-line.png
traincv/views/labeling/labelme/icons/color.png
traincv/views/labeling/labelme/icons/color_line.png
traincv/views/labeling/labelme/icons/copy.png
traincv/views/labeling/labelme/icons/delete.png
traincv-0.0.1.dist-info/LICENSE.md
traincv-0.0.1.dist-info/METADATA
traincv-0.0.1.dist-info/WHEEL
traincv-0.0.1.dist-info/entry_points.txt
traincv-0.0.1.dist-info/top_level.txt
traincv-0.0.1.dist-info/RECORD
