Metadata-Version: 2.1
Name: traincv
Version: 0.0.1
Summary: No-code Labeling and Training Toolkit for Computer Vision
Home-page: https://github.com/nrl-ai/traincv
Author: Viet-Anh Nguyen
Author-email: vietanh.dev@gmail.com
License: GPLv3
Keywords: Image Annotation,Machine Learning,Deep Learning
Classifier: Intended Audience :: Developers
Classifier: Intended Audience :: Science/Research
Classifier: Natural Language :: English
Classifier: Operating System :: OS Independent
Classifier: Programming Language :: Python
Classifier: Programming Language :: Python :: 3.7
Classifier: Programming Language :: Python :: 3.8
Classifier: Programming Language :: Python :: 3.9
Classifier: Programming Language :: Python :: 3 :: Only
License-File: LICENSE.md
Requires-Dist: imgviz (>=0.11)
Requires-Dist: matplotlib (<3.3)
Requires-Dist: natsort (>=7.1.0)
Requires-Dist: numpy
Requires-Dist: Pillow (>=2.8)
Requires-Dist: PyYAML
Requires-Dist: termcolor
Requires-Dist: pyqtgraph
Requires-Dist: pandas
Requires-Dist: psutil
Requires-Dist: opencv-python-headless
Requires-Dist: imutils
Requires-Dist: PyQt5 (>=5.15.7) ; platform_system != "Darwin"
